nbdev_template/__init__.py
nbdev_template/_nbdev.py
nbdev_template/inventory.py
villaInventorySdk/__init__.py
villaInventorySdk/_nbdev.py
villaInventorySdk/inventory.py
villaInventorySdk/schema.py
villaProductSdk/__init__.py
villaProductSdk/_nbdev.py
villaProductSdk/inventory.py
villaProductSdk/products.py
villaProductSdk/schema.py
villaProductSdk-0.0.20.dist-info/LICENSE
villaProductSdk-0.0.20.dist-info/METADATA
villaProductSdk-0.0.20.dist-info/WHEEL
villaProductSdk-0.0.20.dist-info/entry_points.txt
villaProductSdk-0.0.20.dist-info/top_level.txt
villaProductSdk-0.0.20.dist-info/RECORD
