Metadata-Version: 2.1
Name: villaProductSdk
Version: 0.0.20
Summary: sdk for getting product information
Home-page: https://github.com/thanakijwanavit/villa-product-sdk/tree/master/
Author: nic wanavit
Author-email: nwanavit@hatari.cc
License: Apache Software License 2.0
Keywords: villa inventory sdk
Platform: UNKNOWN
Classifier: Development Status :: 3 - Alpha
Classifier: Intended Audience :: Developers
Classifier: License :: OSI Approved :: Apache Software License
Classifier: Natural Language :: English
Classifier: Programming Language :: Python :: 3.6
Classifier: Programming Language :: Python :: 3.7
Classifier: Programming Language :: Python :: 3.8
Requires-Python: >=3.6
Requires-Dist: dataclasses-json
Requires-Dist: boto3
Requires-Dist: requests
Requires-Dist: lambdasdk
Requires-Dist: s3bz
Requires-Dist: ujson
Requires-Dist: awsSchema
Requires-Dist: urllib3 (==1.25.10)
Requires-Dist: nicHelper
